tests/__init__.py
tests/text_Summarizer.py
text_processor/__init__.py
text_processor/summarizer.py
textSummarizerBC-0.1.0.dist-info/METADATA
textSummarizerBC-0.1.0.dist-info/WHEEL
textSummarizerBC-0.1.0.dist-info/top_level.txt
textSummarizerBC-0.1.0.dist-info/RECORD
